LICENSE
resolve_name_clash/__init__.py
resolve_name_clash/resolve_name_clash.py
resolve_name_clash/tests/__init__.py
resolve_name_clash/tests/test_resolve_name_clash.py
resolve_name_clash-0.1.3.dist-info/entry_points.txt
resolve_name_clash-0.1.3.dist-info/LICENSE
resolve_name_clash-0.1.3.dist-info/WHEEL
resolve_name_clash-0.1.3.dist-info/METADATA
resolve_name_clash-0.1.3.dist-info/RECORD
